cloudformation_yaml_generator/__init__.py
cloudformation_yaml_generator/generator.py
cloudformation_yaml_generator-0.1.0.dist-info/LICENSE
cloudformation_yaml_generator-0.1.0.dist-info/METADATA
cloudformation_yaml_generator-0.1.0.dist-info/WHEEL
cloudformation_yaml_generator-0.1.0.dist-info/top_level.txt
cloudformation_yaml_generator-0.1.0.dist-info/RECORD
