Metadata-Version: 2.1
Name: cloudformation-yaml-generator
Version: 0.1.0
Summary: A Python package to generate AWS CloudFormation YAML templates dynamically
Home-page: https://github.com/yourusername/cloudformation-yaml-generator
Author: amit p
Author-email: amitpotdar31@example.com
License: UNKNOWN
Platform: UNKNOWN
Classifier: Programming Language :: Python :: 3
Classifier: License :: OSI Approved :: MIT License
Classifier: Operating System :: OS Independent
Requires-Python: >=3.6
License-File: LICENSE
Requires-Dist: pyyaml
